mypackage/__init__.py
mypackage/__version__.py
mypackage/str2hex.py
str2hex-1.0.0.dist-info/LICENSE
str2hex-1.0.0.dist-info/METADATA
str2hex-1.0.0.dist-info/WHEEL
str2hex-1.0.0.dist-info/top_level.txt
str2hex-1.0.0.dist-info/RECORD
