Metadata-Version: 2.1
Name: str2hex
Version: 1.0.0
Summary: string to hex format.
Home-page: https://github.com/me/myproject
Author: emwzq
Author-email: emwzq@163.com
License: MIT
Platform: UNKNOWN
Classifier: License :: OSI Approved :: MIT License
Classifier: Programming Language :: Python
Classifier: Programming Language :: Python :: 3
Classifier: Programming Language :: Python :: 3.6
Classifier: Programming Language :: Python :: Implementation :: CPython
Classifier: Programming Language :: Python :: Implementation :: PyPy
Requires-Python: >=3.6.0
Requires-Dist: str2hex
